README
setup.cfg
setup.py
duplex/__init__.py
duplex/async.py
duplex/protocol.py
duplex/sync.py
duplex/test_async.py
duplex/test_sync.py
duplex/version.py
duplex/ws4py.py
duplex.egg-info/PKG-INFO
duplex.egg-info/SOURCES.txt
duplex.egg-info/dependency_links.txt
duplex.egg-info/requires.txt
duplex.egg-info/top_level.txt
duplex/codecs/__init__.py
duplex/codecs/json.py