Metadata-Version: 1.1
Name: duplex
Version: 0.1.4
Summary: Full duplex RPC and service toolkit
Home-page: https://github.com/progrium/duplex
Author: Jeff Lindsay
Author-email: progrium@gmail.com
License: MIT
Platform: all
Classifier: Intended Audience :: Developers
Classifier: License :: OSI Approved :: MIT License
Classifier: Operating System :: OS Independent
Classifier: Programming Language :: Python
Classifier: Programming Language :: Python :: 3
Classifier: Programming Language :: Python :: 3.3
Classifier: Programming Language :: Python :: 3.4
Classifier: Programming Language :: Python :: 3.5
